chatterbox_io/__init__.py
chatterbox_io/client.py
chatterbox_io/models.py
chatterbox_io/websocket.py
chatterbox_io-1.4.1.dist-info/licenses/LICENSE.md
chatterbox_io-1.4.1.dist-info/METADATA
chatterbox_io-1.4.1.dist-info/WHEEL
chatterbox_io-1.4.1.dist-info/top_level.txt
chatterbox_io-1.4.1.dist-info/RECORD
