Metadata-Version: 2.4
Name: chatterbox-io
Version: 1.4.1
Summary: Python client for ChatterBox - Integrate with Zoom, Teams, Google Meet for real-time transcripts
Home-page: https://github.com/OverQuotaAI/chatterbox-python
Author: OverQuotaAI
Author-email: alex@chatter-box.io
Classifier: Development Status :: 5 - Production/Stable
Classifier: Intended Audience :: Developers
Classifier: License :: OSI Approved :: MIT License
Classifier: Operating System :: OS Independent
Classifier: Programming Language :: Python :: 3
Classifier: Programming Language :: Python :: 3.7
Classifier: Programming Language :: Python :: 3.8
Classifier: Programming Language :: Python :: 3.9
Classifier: Programming Language :: Python :: 3.10
Classifier: Programming Language :: Python :: 3.11
Requires-Python: >=3.7
License-File: LICENSE.md
Requires-Dist: aiohttp>=3.8.0
Requires-Dist: requests>=2.32.3
Requires-Dist: python-socketio>=5.12.1
Requires-Dist: pydantic>=2.11.1
Provides-Extra: dev
Requires-Dist: pytest>=8.3.5; extra == "dev"
Requires-Dist: black>=25.1.0; extra == "dev"
Requires-Dist: isort>=6.0.1; extra == "dev"
Requires-Dist: flake8>=7.2.0; extra == "dev"
Dynamic: author
Dynamic: author-email
Dynamic: classifier
Dynamic: description
Dynamic: description-content-type
Dynamic: home-page
Dynamic: license-file
Dynamic: provides-extra
Dynamic: requires-dist
Dynamic: requires-python
Dynamic: summary
